mkdocs_confluence/__init__.py
mkdocs_confluence/plugin.py
mkdocs_confluence-0.2.2.dist-info/LICENSE
mkdocs_confluence-0.2.2.dist-info/METADATA
mkdocs_confluence-0.2.2.dist-info/WHEEL
mkdocs_confluence-0.2.2.dist-info/entry_points.txt
mkdocs_confluence-0.2.2.dist-info/top_level.txt
mkdocs_confluence-0.2.2.dist-info/RECORD
